fhurl.py
fhurl-0.1.8.dist-info/DESCRIPTION.rst
fhurl-0.1.8.dist-info/METADATA
fhurl-0.1.8.dist-info/metadata.json
fhurl-0.1.8.dist-info/RECORD
fhurl-0.1.8.dist-info/top_level.txt
fhurl-0.1.8.dist-info/WHEEL
