Metadata-Version: 2.0
Name: fhurl
Version: 0.1.8
Summary: Django generic form handler view
Home-page: http://packages.python.org/fhurl/
Author: Amit Upadhyay
Author-email: upadhyay@gmail.com
License: BSD
Platform: UNKNOWN
Requires-Dist: smarturls
